Metadata-Version: 1.0
Name: cnfx
Version: 0.0.4
Summary: CNFX - A base -1 + i CNF encoder for complex field operations.
Home-page: https://github.com/maxtuno/CNFX
Author: Oscar Riveros
Author-email: oscar.riveros@gmail.com
License: Proprietary
Platform: UNKNOWN
